redturtle.scale-1.0a2-py3.11-nspkg.pth
redturtle/scale/__init__.py
redturtle/scale/configure.zcml
redturtle/scale/interfaces.py
redturtle/scale/patches.py
redturtle/scale/permissions.zcml
redturtle/scale/scale.py
redturtle/scale/setuphandlers.py
redturtle/scale/storage.py
redturtle/scale/testing.py
redturtle/scale/browser/__init__.py
redturtle/scale/browser/configure.zcml
redturtle/scale/locales/README.rst
redturtle/scale/locales/__init__.py
redturtle/scale/locales/redturtle.scale.pot
redturtle/scale/locales/update.py
redturtle/scale/locales/update.sh
redturtle/scale/locales/en/LC_MESSAGES/redturtle.scale.po
redturtle/scale/profiles/default/browserlayer.xml
redturtle/scale/profiles/default/catalog.xml
redturtle/scale/profiles/default/metadata.xml
redturtle/scale/profiles/default/registry/main.xml
redturtle/scale/profiles/uninstall/browserlayer.xml
redturtle/scale/tests/__init__.py
redturtle/scale/tests/test_setup.py
redturtle_scale-1.0a2.dist-info/licenses/LICENSE.GPL
redturtle_scale-1.0a2.dist-info/licenses/LICENSE.rst
redturtle_scale-1.0a2.dist-info/METADATA
redturtle_scale-1.0a2.dist-info/WHEEL
redturtle_scale-1.0a2.dist-info/entry_points.txt
redturtle_scale-1.0a2.dist-info/namespace_packages.txt
redturtle_scale-1.0a2.dist-info/top_level.txt
redturtle_scale-1.0a2.dist-info/RECORD
